hebcal_provider.py
prompts.py
nucore_hebcal_provider-1.0.0.dist-info/METADATA
nucore_hebcal_provider-1.0.0.dist-info/WHEEL
nucore_hebcal_provider-1.0.0.dist-info/top_level.txt
nucore_hebcal_provider-1.0.0.dist-info/RECORD
