Metadata-Version: 2.4
Name: nucore_hebcal_provider
Version: 1.0.0
Summary: Hebrew Calendar Provider for NuCore
Author-email: Michel Kohanim <michel@universal-devices.com>
License: MIT
Project-URL: Homepage, https://github.com/NuCoreAI/hebcal_provider
Requires-Python: >=3.10
Requires-Dist: aiohttp>=3.8.0
Requires-Dist: nucore_holiday_provider>=1.0.0
